django_bulk_triggers/__init__.py
django_bulk_triggers/changeset.py
django_bulk_triggers/conditions.py
django_bulk_triggers/constants.py
django_bulk_triggers/context.py
django_bulk_triggers/debug_utils.py
django_bulk_triggers/decorators.py
django_bulk_triggers/dispatcher.py
django_bulk_triggers/enums.py
django_bulk_triggers/factory.py
django_bulk_triggers/handler.py
django_bulk_triggers/helpers.py
django_bulk_triggers/manager.py
django_bulk_triggers/models.py
django_bulk_triggers/operations/__init__.py
django_bulk_triggers/operations/analyzer.py
django_bulk_triggers/operations/bulk_executor.py
django_bulk_triggers/operations/coordinator.py
django_bulk_triggers/operations/mti_handler.py
django_bulk_triggers/queryset.py
django_bulk_triggers/registry.py
django_bulk_triggers-0.2.4.dist-info/LICENSE
django_bulk_triggers-0.2.4.dist-info/METADATA
django_bulk_triggers-0.2.4.dist-info/WHEEL
django_bulk_triggers-0.2.4.dist-info/RECORD
